Metadata-Version: 2.1
Name: python-translator
Version: 1.0.2
Summary: Translate text from one language to another.
Home-page: https://github.com/bentettmar/python-translator
Author: Ben Tettmar
License: MIT
Platform: UNKNOWN
Classifier: Development Status :: 5 - Production/Stable
Classifier: Intended Audience :: Developers
Classifier: License :: OSI Approved :: MIT License
Classifier: Programming Language :: Python :: 3.6
Classifier: Programming Language :: Python :: 3.7
Classifier: Programming Language :: Python :: 3.8
Classifier: Programming Language :: Python :: 3.9
Classifier: Programming Language :: Python :: 3.10
Requires: requests
Requires: bs4
